{
  "meta": {
    "user": "bobi",
    "subject": "gen",
    "lesson": 20,
    "generated": "2026-04-25",
    "total": 20
  },
  "questions": [
    {
      "id": 1,
      "module_id": 1,
      "card_id": 3,
      "question": "На колко отделни страни се разпадна СССР в края на 20 век?",
      "options": [
        {
          "id": "a",
          "text": "На 10 страни",
          "correct": false
        },
        {
          "id": "b",
          "text": "На 15 страни",
          "correct": true
        },
        {
          "id": "c",
          "text": "На 20 страни",
          "correct": false
        }
      ],
      "explanation": "СССР се разпадна на точно 15 отделни страни, всяка от които започна да се управлява самостоятелно."
    },
    {
      "id": 2,
      "module_id": 1,
      "card_id": 4,
      "question": "На колко страни се разпадна Югославия?",
      "options": [
        {
          "id": "a",
          "text": "На 4 страни",
          "correct": false
        },
        {
          "id": "b",
          "text": "На 8 страни",
          "correct": false
        },
        {
          "id": "c",
          "text": "На 6 страни",
          "correct": true
        }
      ],
      "explanation": "Югославия се разпадна на 6 страни: Словения, Хърватия, Босна, Сърбия, Черна гора и Македония."
    },
    {
      "id": 3,
      "module_id": 1,
      "card_id": 5,
      "question": "Колко страни има на Балканския полуостров днес?",
      "options": [
        {
          "id": "a",
          "text": "7 страни",
          "correct": false
        },
        {
          "id": "b",
          "text": "11 страни",
          "correct": true
        },
        {
          "id": "c",
          "text": "15 страни",
          "correct": false
        }
      ],
      "explanation": "Днес на Балканите има 11 страни, една от които е България."
    },
    {
      "id": 4,
      "module_id": 2,
      "card_id": 2,
      "question": "Кога е основан Съветът на Европа, от който започна пътят към ЕС?",
      "options": [
        {
          "id": "a",
          "text": "На 9 май 1949 г.",
          "correct": true
        },
        {
          "id": "b",
          "text": "На 9 май 1957 г.",
          "correct": false
        },
        {
          "id": "c",
          "text": "На 9 май 1989 г.",
          "correct": false
        }
      ],
      "explanation": "Съветът на Европа е основан на 9 май 1949 г. и затова 9 май се празнува като Ден на Европа."
    },
    {
      "id": 5,
      "module_id": 2,
      "card_id": 3,
      "question": "Колко страни членуват в Европейския съюз?",
      "options": [
        {
          "id": "a",
          "text": "25 страни",
          "correct": false
        },
        {
          "id": "b",
          "text": "30 страни",
          "correct": false
        },
        {
          "id": "c",
          "text": "27 страни",
          "correct": true
        }
      ],
      "explanation": "В Европейския съюз членуват 27 страни, които работят заедно за по-добър живот на гражданите си."
    },
    {
      "id": 6,
      "module_id": 2,
      "card_id": 4,
      "question": "В кой град заседава Европейският парламент?",
      "options": [
        {
          "id": "a",
          "text": "В Брюксел",
          "correct": false
        },
        {
          "id": "b",
          "text": "В Страсбург",
          "correct": true
        },
        {
          "id": "c",
          "text": "В Берлин",
          "correct": false
        }
      ],
      "explanation": "Европейският парламент заседава в град Страсбург, където представители от всички страни гласуват за общи правила."
    },
    {
      "id": 7,
      "module_id": 3,
      "card_id": 2,
      "question": "Коя е най-малката страна в Европа по площ?",
      "options": [
        {
          "id": "a",
          "text": "Монако",
          "correct": false
        },
        {
          "id": "b",
          "text": "Андора",
          "correct": false
        },
        {
          "id": "c",
          "text": "Ватикана",
          "correct": true
        }
      ],
      "explanation": "Ватикана е най-малката страна в Европа с площ само 0,44 кв. км."
    },
    {
      "id": 8,
      "module_id": 3,
      "card_id": 3,
      "question": "Кои три страни са най-населените в Европа?",
      "options": [
        {
          "id": "a",
          "text": "Русия, Германия и Франция",
          "correct": true
        },
        {
          "id": "b",
          "text": "Русия, Испания и Италия",
          "correct": false
        },
        {
          "id": "c",
          "text": "Германия, Полша и Румъния",
          "correct": false
        }
      ],
      "explanation": "Русия, Германия и Франция са страните с най-много население в Европа."
    },
    {
      "id": 9,
      "module_id": 3,
      "card_id": 5,
      "question": "Как се управлява страна монархия?",
      "options": [
        {
          "id": "a",
          "text": "От министър-председател, избран от народа",
          "correct": false
        },
        {
          "id": "b",
          "text": "От президент, избран на избори",
          "correct": false
        },
        {
          "id": "c",
          "text": "От крал или кралица",
          "correct": true
        }
      ],
      "explanation": "В монархиите управлява крал или кралица, например в Испания и Белгия."
    },
    {
      "id": 10,
      "module_id": 4,
      "card_id": 1,
      "question": "От колко страни се състои Съветът на Европа?",
      "options": [
        {
          "id": "a",
          "text": "От 27 страни",
          "correct": false
        },
        {
          "id": "b",
          "text": "От 47 страни",
          "correct": true
        },
        {
          "id": "c",
          "text": "От 32 страни",
          "correct": false
        }
      ],
      "explanation": "Съветът на Европа включва 47 страни и се грижи за правата на човека и демокрацията."
    },
    {
      "id": 11,
      "module_id": 4,
      "card_id": 2,
      "question": "Колко страни членуват в НАТО?",
      "options": [
        {
          "id": "a",
          "text": "27 страни",
          "correct": false
        },
        {
          "id": "b",
          "text": "47 страни",
          "correct": false
        },
        {
          "id": "c",
          "text": "32 страни",
          "correct": true
        }
      ],
      "explanation": "В НАТО членуват 32 страни от Европа и Северна Америка, които си помагат за защита и сигурност."
    },
    {
      "id": 12,
      "module_id": 4,
      "card_id": 3,
      "question": "Кога България влезе в НАТО?",
      "options": [
        {
          "id": "a",
          "text": "На 29 март 2004 г.",
          "correct": true
        },
        {
          "id": "b",
          "text": "На 1 януари 2007 г.",
          "correct": false
        },
        {
          "id": "c",
          "text": "На 9 май 1999 г.",
          "correct": false
        }
      ],
      "explanation": "България стана член на НАТО на 29 март 2004 г., а в ЕС влезе по-късно – на 1 януари 2007 г."
    },
    {
      "id": 13,
      "module_id": 0,
      "card_id": 0,
      "question": "Коя страна е островна в Европа?",
      "options": [
        {
          "id": "a",
          "text": "Австрия",
          "correct": false
        },
        {
          "id": "b",
          "text": "Великобритания",
          "correct": true
        },
        {
          "id": "c",
          "text": "Унгария",
          "correct": false
        }
      ],
      "explanation": "Великобритания е островна страна, защото около нея е само море."
    },
    {
      "id": 14,
      "module_id": 0,
      "card_id": 0,
      "question": "Кога България влезе в Европейския съюз?",
      "options": [
        {
          "id": "a",
          "text": "На 1 януари 2004 г.",
          "correct": false
        },
        {
          "id": "b",
          "text": "На 1 януари 2007 г.",
          "correct": true
        },
        {
          "id": "c",
          "text": "На 1 януари 2010 г.",
          "correct": false
        }
      ],
      "explanation": "България стана член на ЕС на 1 януари 2007 г. и оттогава се ползва от ползите на членството."
    },
    {
      "id": 15,
      "module_id": 0,
      "card_id": 0,
      "question": "Коя е причината страните в ЕС да работят заедно?",
      "options": [
        {
          "id": "a",
          "text": "Защото имат един и същи език",
          "correct": false
        },
        {
          "id": "b",
          "text": "Защото заедно са по-силни и решават проблемите по-лесно",
          "correct": true
        },
        {
          "id": "c",
          "text": "Защото имат обща армия",
          "correct": false
        }
      ],
      "explanation": "Страните в ЕС работят заедно, защото така са по-силни и животът на гражданите им е по-добър."
    },
    {
      "id": 16,
      "module_id": 0,
      "card_id": 0,
      "question": "Какво означава, че Европа се е разделила на Западна и Източна след Втората световна война?",
      "options": [
        {
          "id": "a",
          "text": "Двете части имали различни правила за живот",
          "correct": true
        },
        {
          "id": "b",
          "text": "Двете части говорели различни езици",
          "correct": false
        },
        {
          "id": "c",
          "text": "Двете части имали различен климат",
          "correct": false
        }
      ],
      "explanation": "След Втората световна война Западна и Източна Европа имали различни правила за живот и управление."
    },
    {
      "id": 17,
      "module_id": 0,
      "card_id": 0,
      "question": "Каква е ползата за гражданите от членството в ЕС?",
      "options": [
        {
          "id": "a",
          "text": "Могат да пътуват, учат и работят свободно в страните от ЕС",
          "correct": true
        },
        {
          "id": "b",
          "text": "Не плащат данъци в никоя страна",
          "correct": false
        },
        {
          "id": "c",
          "text": "Получават безплатно жилище в друга страна",
          "correct": false
        }
      ],
      "explanation": "В ЕС хората могат свободно да пътуват, учат и работят в различни страни без специални разрешения."
    },
    {
      "id": 18,
      "module_id": 0,
      "card_id": 0,
      "question": "Коя страна се стреми да стане член на ЕС в момента?",
      "options": [
        {
          "id": "a",
          "text": "Русия",
          "correct": false
        },
        {
          "id": "b",
          "text": "Беларус",
          "correct": false
        },
        {
          "id": "c",
          "text": "Украйна",
          "correct": true
        }
      ],
      "explanation": "Украйна в момента се стреми да стане член на ЕС и процесът на присъединяване продължава."
    },
    {
      "id": 19,
      "module_id": 0,
      "card_id": 0,
      "question": "Коя от изброените страни е република?",
      "options": [
        {
          "id": "a",
          "text": "Испания",
          "correct": false
        },
        {
          "id": "b",
          "text": "Белгия",
          "correct": false
        },
        {
          "id": "c",
          "text": "България",
          "correct": true
        }
      ],
      "explanation": "България е република – управлява се от президент, за разлика от Испания и Белгия, които са монархии."
    },
    {
      "id": 20,
      "module_id": 0,
      "card_id": 0,
      "question": "Към какво се обръща човек, ако правата му са нарушени в някоя европейска страна?",
      "options": [
        {
          "id": "a",
          "text": "Към Европейския парламент в Страсбург",
          "correct": false
        },
        {
          "id": "b",
          "text": "Към Европейския съд по правата на човека",
          "correct": true
        },
        {
          "id": "c",
          "text": "Към щаба на НАТО",
          "correct": false
        }
      ],
      "explanation": "Европейският съд по правата на човека е институцията към Съвета на Европа, която защитава правата на хората."
    }
  ]
}