{
  "meta": {
    "user": "bobi",
    "subject": "geo",
    "lesson": 20,
    "generated": "2026-04-25",
    "total": 20
  },
  "questions": [
    {
      "id": 1,
      "module_id": 1,
      "card_id": 2,
      "question": "На колко страни беше разделена Германия след Втората световна война?",
      "options": [
        {
          "id": "a",
          "text": "На три страни",
          "correct": false
        },
        {
          "id": "b",
          "text": "На две страни",
          "correct": true
        },
        {
          "id": "c",
          "text": "На четири страни",
          "correct": false
        }
      ],
      "explanation": "След Втората световна война Германия се раздели точно на две отделни страни, а после се обедини отново през 1990 г."
    },
    {
      "id": 2,
      "module_id": 1,
      "card_id": 3,
      "question": "На колко отделни държави се разпадна СССР в началото на 90-те години?",
      "options": [
        {
          "id": "a",
          "text": "На 10 държави",
          "correct": false
        },
        {
          "id": "b",
          "text": "На 20 държави",
          "correct": false
        },
        {
          "id": "c",
          "text": "На 15 държави",
          "correct": true
        }
      ],
      "explanation": "СССР се разпадна точно на 15 отделни държави, сред които са Русия, Украйна и Грузия."
    },
    {
      "id": 3,
      "module_id": 1,
      "card_id": 5,
      "question": "Колко страни има на Балканския полуостров днес?",
      "options": [
        {
          "id": "a",
          "text": "8 страни",
          "correct": false
        },
        {
          "id": "b",
          "text": "11 страни",
          "correct": true
        },
        {
          "id": "c",
          "text": "14 страни",
          "correct": false
        }
      ],
      "explanation": "На Балканския полуостров има точно 11 страни, включително България, Гърция, Сърбия и Румъния."
    },
    {
      "id": 4,
      "module_id": 2,
      "card_id": 7,
      "question": "Кога България влезе в Европейския съюз?",
      "options": [
        {
          "id": "a",
          "text": "През 2004 г.",
          "correct": false
        },
        {
          "id": "b",
          "text": "През 2007 г.",
          "correct": true
        },
        {
          "id": "c",
          "text": "През 2010 г.",
          "correct": false
        }
      ],
      "explanation": "България стана член на ЕС през 2007 г., след като изпълни необходимите изисквания."
    },
    {
      "id": 5,
      "module_id": 2,
      "card_id": 9,
      "question": "Какво е НАТО?",
      "options": [
        {
          "id": "a",
          "text": "Икономически съюз за търговия",
          "correct": false
        },
        {
          "id": "b",
          "text": "Организация за защита правата на хората",
          "correct": false
        },
        {
          "id": "c",
          "text": "Военен съюз, в който членовете се защитават взаимно",
          "correct": true
        }
      ],
      "explanation": "НАТО е военен съюз на страни от Европа и Америка, чиято цел е взаимна защита при нападение."
    },
    {
      "id": 6,
      "module_id": 2,
      "card_id": 10,
      "question": "В кой град се намира Европейският парламент?",
      "options": [
        {
          "id": "a",
          "text": "В Париж",
          "correct": false
        },
        {
          "id": "b",
          "text": "В Берлин",
          "correct": false
        },
        {
          "id": "c",
          "text": "В Страсбург",
          "correct": true
        }
      ],
      "explanation": "Европейският парламент се намира в Страсбург, където депутати от всички страни на ЕС гласуват за общи закони."
    },
    {
      "id": 7,
      "module_id": 3,
      "card_id": 12,
      "question": "Коя от следните страни е континентална (без излаз на море)?",
      "options": [
        {
          "id": "a",
          "text": "Гърция",
          "correct": false
        },
        {
          "id": "b",
          "text": "Австрия",
          "correct": true
        },
        {
          "id": "c",
          "text": "Испания",
          "correct": false
        }
      ],
      "explanation": "Австрия е континентална страна — тя е изцяло на сушата и няма излаз на море."
    },
    {
      "id": 8,
      "module_id": 3,
      "card_id": 13,
      "question": "Кои от следните страни са островни?",
      "options": [
        {
          "id": "a",
          "text": "Италия и Португалия",
          "correct": false
        },
        {
          "id": "b",
          "text": "Великобритания и Ирландия",
          "correct": true
        },
        {
          "id": "c",
          "text": "Франция и Германия",
          "correct": false
        }
      ],
      "explanation": "Великобритания и Ирландия са островни страни — те се намират на острови, заобиколени от вода."
    },
    {
      "id": 9,
      "module_id": 3,
      "card_id": 15,
      "question": "Коя е най-малката страна в Европа по площ?",
      "options": [
        {
          "id": "a",
          "text": "Сан Марино",
          "correct": false
        },
        {
          "id": "b",
          "text": "Монако",
          "correct": true
        },
        {
          "id": "c",
          "text": "Лихтенщайн",
          "correct": false
        }
      ],
      "explanation": "Монако е най-малката страна в Европа по площ — тя е толкова малка, че се събира в един град."
    },
    {
      "id": 10,
      "module_id": 4,
      "card_id": 16,
      "question": "Какво е характерно за страна-република?",
      "options": [
        {
          "id": "a",
          "text": "Начело стои крал, който наследява властта",
          "correct": false
        },
        {
          "id": "b",
          "text": "Хората избират президент или правителство чрез гласуване",
          "correct": true
        },
        {
          "id": "c",
          "text": "Страната се управлява от военни командири",
          "correct": false
        }
      ],
      "explanation": "В република хората сами избират своите лидери чрез гласуване, а не властта се предава по наследство."
    },
    {
      "id": 11,
      "module_id": 4,
      "card_id": 18,
      "question": "Колко квадратни километра е Ватикан?",
      "options": [
        {
          "id": "a",
          "text": "4,4 кв. км",
          "correct": false
        },
        {
          "id": "b",
          "text": "44 кв. км",
          "correct": false
        },
        {
          "id": "c",
          "text": "0,44 кв. км",
          "correct": true
        }
      ],
      "explanation": "Ватикан е само 0,44 кв. км — това го прави най-малката страна в света."
    },
    {
      "id": 12,
      "module_id": 4,
      "card_id": 19,
      "question": "С какво е известно Монако в света на спорта?",
      "options": [
        {
          "id": "a",
          "text": "С олимпийски игри по плуване",
          "correct": false
        },
        {
          "id": "b",
          "text": "С автомобилни надбягвания Формула 1",
          "correct": true
        },
        {
          "id": "c",
          "text": "С международен турнир по тенис на маса",
          "correct": false
        }
      ],
      "explanation": "Монако е известно с надбягванията от Формула 1, които се провеждат по улиците на страната."
    },
    {
      "id": 13,
      "module_id": 0,
      "card_id": 0,
      "question": "Какво показва политическата карта?",
      "options": [
        {
          "id": "a",
          "text": "Реките и планините в Европа",
          "correct": false
        },
        {
          "id": "b",
          "text": "Страните и техните граници",
          "correct": true
        },
        {
          "id": "c",
          "text": "Климатичните зони на континента",
          "correct": false
        }
      ],
      "explanation": "Политическата карта показва страните и техните граници, а не природни обекти."
    },
    {
      "id": 14,
      "module_id": 0,
      "card_id": 0,
      "question": "На колко страни се разпадна Югославия?",
      "options": [
        {
          "id": "a",
          "text": "На 4 страни",
          "correct": false
        },
        {
          "id": "b",
          "text": "На 6 страни",
          "correct": true
        },
        {
          "id": "c",
          "text": "На 8 страни",
          "correct": false
        }
      ],
      "explanation": "Югославия се разпадна на 6 страни след войни и конфликти, включително Сърбия, Хърватия и Словения."
    },
    {
      "id": 15,
      "module_id": 0,
      "card_id": 0,
      "question": "Кога България стана член на НАТО?",
      "options": [
        {
          "id": "a",
          "text": "През 2004 г.",
          "correct": true
        },
        {
          "id": "b",
          "text": "През 2007 г.",
          "correct": false
        },
        {
          "id": "c",
          "text": "През 1999 г.",
          "correct": false
        }
      ],
      "explanation": "България влезе в НАТО през 2004 г., три години преди да се присъедини към ЕС."
    },
    {
      "id": 16,
      "module_id": 0,
      "card_id": 0,
      "question": "Колко страни членуват в Европейския съюз?",
      "options": [
        {
          "id": "a",
          "text": "47 страни",
          "correct": false
        },
        {
          "id": "b",
          "text": "27 страни",
          "correct": true
        },
        {
          "id": "c",
          "text": "35 страни",
          "correct": false
        }
      ],
      "explanation": "ЕС се състои от 27 европейски страни, които работят заедно и споделят закони, пари и отворени граници."
    },
    {
      "id": 17,
      "module_id": 0,
      "card_id": 0,
      "question": "Коя организация защитава правата на хората в Европа и има 47 страни членки?",
      "options": [
        {
          "id": "a",
          "text": "НАТО",
          "correct": false
        },
        {
          "id": "b",
          "text": "Европейският съюз",
          "correct": false
        },
        {
          "id": "c",
          "text": "Съветът на Европа",
          "correct": true
        }
      ],
      "explanation": "Съветът на Европа е организация на 47 страни, чиято основна цел е да защитава правата на хората."
    },
    {
      "id": 18,
      "module_id": 0,
      "card_id": 0,
      "question": "Кои страни са примери за полуостровни страни в Европа?",
      "options": [
        {
          "id": "a",
          "text": "Австрия, Унгария и Швейцария",
          "correct": false
        },
        {
          "id": "b",
          "text": "Великобритания, Ирландия и Исландия",
          "correct": false
        },
        {
          "id": "c",
          "text": "Италия, Гърция и Испания",
          "correct": true
        }
      ],
      "explanation": "Италия, Гърция и Испания са полуостровни страни — те са заобиколени от вода само от три страни и имат излаз на море."
    },
    {
      "id": 19,
      "module_id": 0,
      "card_id": 0,
      "question": "В коя страна се управлява от крал или кралица, наследили властта?",
      "options": [
        {
          "id": "a",
          "text": "В република",
          "correct": false
        },
        {
          "id": "b",
          "text": "В монархия",
          "correct": true
        },
        {
          "id": "c",
          "text": "В съюз",
          "correct": false
        }
      ],
      "explanation": "В монархия начело стои крал или кралица, които наследяват властта от своите родители."
    },
    {
      "id": 20,
      "module_id": 0,
      "card_id": 0,
      "question": "Защо страните работят заедно в организации като ЕС и НАТО?",
      "options": [
        {
          "id": "a",
          "text": "За да контролират по-малките страни",
          "correct": false
        },
        {
          "id": "b",
          "text": "Защото заедно са по-силни и могат да решават проблеми по-добре",
          "correct": true
        },
        {
          "id": "c",
          "text": "За да имат обща армия, която воюва с останалия свят",
          "correct": false
        }
      ],
      "explanation": "Страните си сътрудничат, защото заедно са по-силни — сътрудничеството носи мир, търговия и по-добър живот за всички."
    }
  ]
}